atlassian/VERSION
atlassian/__init__.py
atlassian/assets.py
atlassian/bamboo.py
atlassian/cloud_admin.py
atlassian/crowd.py
atlassian/errors.py
atlassian/insight.py
atlassian/jira.py
atlassian/marketplace.py
atlassian/portfolio.py
atlassian/py.typed
atlassian/request_utils.py
atlassian/rest_client.py
atlassian/service_desk.py
atlassian/statuspage.py
atlassian/typehints.py
atlassian/utils.py
atlassian/xray.py
atlassian/bitbucket/__init__.py
atlassian/bitbucket/base.py
atlassian/bitbucket/cloud/__init__.py
atlassian/bitbucket/cloud/base.py
atlassian/bitbucket/cloud/common/__init__.py
atlassian/bitbucket/cloud/common/builds.py
atlassian/bitbucket/cloud/common/comments.py
atlassian/bitbucket/cloud/common/users.py
atlassian/bitbucket/cloud/repositories/__init__.py
atlassian/bitbucket/cloud/repositories/branchRestrictions.py
atlassian/bitbucket/cloud/repositories/commits.py
atlassian/bitbucket/cloud/repositories/defaultReviewers.py
atlassian/bitbucket/cloud/repositories/deploymentEnvironments.py
atlassian/bitbucket/cloud/repositories/diffstat.py
atlassian/bitbucket/cloud/repositories/groupPermissions.py
atlassian/bitbucket/cloud/repositories/hooks.py
atlassian/bitbucket/cloud/repositories/issues.py
atlassian/bitbucket/cloud/repositories/pipelines.py
atlassian/bitbucket/cloud/repositories/pullRequests.py
atlassian/bitbucket/cloud/repositories/refs.py
atlassian/bitbucket/cloud/repositories/repositoryVariables.py
atlassian/bitbucket/cloud/workspaces/__init__.py
atlassian/bitbucket/cloud/workspaces/members.py
atlassian/bitbucket/cloud/workspaces/permissions.py
atlassian/bitbucket/cloud/workspaces/projects.py
atlassian/bitbucket/server/__init__.py
atlassian/bitbucket/server/base.py
atlassian/bitbucket/server/globalPermissions.py
atlassian/bitbucket/server/common/__init__.py
atlassian/bitbucket/server/common/permissions.py
atlassian/bitbucket/server/projects/__init__.py
atlassian/bitbucket/server/projects/repos/__init__.py
atlassian/confluence/__init__.py
thopx14_atlassian_python_api-4.0.5.dist-info/licenses/LICENSE
thopx14_atlassian_python_api-4.0.5.dist-info/METADATA
thopx14_atlassian_python_api-4.0.5.dist-info/WHEEL
thopx14_atlassian_python_api-4.0.5.dist-info/top_level.txt
thopx14_atlassian_python_api-4.0.5.dist-info/RECORD
