Metadata-Version: 2.4
Name: thopx14-atlassian-python-api
Version: 4.0.5
Summary: Python Atlassian REST API Wrapper
Home-page: https://github.com/thopx14/atlassian-python-api
Download-URL: https://github.com/thopx14/atlassian-python-api
Author: Matt Harasymczuk
Author-email: matt@astrotech.io
Maintainer: Gonchik Tsymzhitov
Maintainer-email: gonchik.tsymzhitov@gmail.com
License: Apache License 2.0
Keywords: atlassian jira core software confluence bitbucket bamboo crowd portfolio tempo servicedesk assets api
Platform: Platform Independent
Classifier: Development Status :: 4 - Beta
Classifier: Environment :: Web Environment
Classifier: Environment :: Console
Classifier: Intended Audience :: Developers
Classifier: Intended Audience :: Education
Classifier: Intended Audience :: Information Technology
Classifier: Intended Audience :: Science/Research
Classifier: Intended Audience :: System Administrators
Classifier: License :: OSI Approved :: Apache Software License
Classifier: Natural Language :: English
Classifier: Operating System :: OS Independent
Classifier: Operating System :: POSIX
Classifier: Operating System :: Unix
Classifier: Operating System :: MacOS :: MacOS X
Classifier: Operating System :: Microsoft :: Windows
Classifier: Programming Language :: Python
Classifier: Programming Language :: Python :: 3.9
Classifier: Programming Language :: Python :: 3.10
Classifier: Programming Language :: Python :: 3.11
Classifier: Programming Language :: Python :: 3.12
Classifier: Programming Language :: Python :: 3.13
Classifier: Topic :: Utilities
Classifier: Topic :: Internet
Classifier: Topic :: Internet :: WWW/HTTP
Classifier: Topic :: Internet :: WWW/HTTP :: Dynamic Content
Classifier: Topic :: Software Development :: Libraries :: Python Modules
Classifier: Topic :: Software Development :: Libraries :: Application Frameworks
License-File: LICENSE
Requires-Dist: deprecated
Requires-Dist: requests
Requires-Dist: oauthlib
Requires-Dist: requests_oauthlib
Requires-Dist: jmespath
Requires-Dist: beautifulsoup4
Requires-Dist: typing-extensions
Provides-Extra: kerberos
Requires-Dist: requests-kerberos; extra == "kerberos"
Dynamic: author
Dynamic: author-email
Dynamic: classifier
Dynamic: description
Dynamic: download-url
Dynamic: home-page
Dynamic: keywords
Dynamic: license
Dynamic: license-file
Dynamic: maintainer
Dynamic: maintainer-email
Dynamic: platform
Dynamic: provides-extra
Dynamic: requires-dist
Dynamic: summary
